CHANGES.txt
LICENSE.txt
README.txt
bootstrap.py
buildout.cfg
setup.py
src/getpaid/__init__.py
src/getpaid.nullpayment.egg-info/PKG-INFO
src/getpaid.nullpayment.egg-info/SOURCES.txt
src/getpaid.nullpayment.egg-info/dependency_links.txt
src/getpaid.nullpayment.egg-info/namespace_packages.txt
src/getpaid.nullpayment.egg-info/not-zip-safe
src/getpaid.nullpayment.egg-info/requires.txt
src/getpaid.nullpayment.egg-info/top_level.txt
src/getpaid/nullpayment/README.txt
src/getpaid/nullpayment/__init__.py
src/getpaid/nullpayment/configure.zcml
src/getpaid/nullpayment/i18n.sh
src/getpaid/nullpayment/interfaces.py
src/getpaid/nullpayment/null.py
src/getpaid/nullpayment/locales/empty.pt
src/getpaid/nullpayment/locales/getpaid.nullpayment.pot
src/getpaid/nullpayment/locales/manual.pot
src/getpaid/nullpayment/locales/en/LC_MESSAGES/getpaid.nullpayment.mo
src/getpaid/nullpayment/locales/en/LC_MESSAGES/getpaid.nullpayment.po
src/getpaid/nullpayment/locales/es/LC_MESSAGES/getpaid.nullpayment.mo
src/getpaid/nullpayment/locales/es/LC_MESSAGES/getpaid.nullpayment.po
src/getpaid/nullpayment/locales/it/LC_MESSAGES/getpaid.nullpayment.mo
src/getpaid/nullpayment/locales/it/LC_MESSAGES/getpaid.nullpayment.po
src/getpaid/nullpayment/locales/ja/LC_MESSAGES/getpaid.nullpayment.mo
src/getpaid/nullpayment/locales/ja/LC_MESSAGES/getpaid.nullpayment.po
src/getpaid/nullpayment/locales/zh/LC_MESSAGES/getpaid.nullpayment.mo
src/getpaid/nullpayment/locales/zh/LC_MESSAGES/getpaid.nullpayment.po